audithub_client/__init__.py
audithub_client/__main__.py
audithub_client/api/__init__.py
audithub_client/api/add_user_to_organization.py
audithub_client/api/create_organization.py
audithub_client/api/create_project.py
audithub_client/api/create_temp_version_via_local_archive.py
audithub_client/api/create_temp_version_via_url.py
audithub_client/api/create_version_via_local_archive.py
audithub_client/api/create_version_via_url.py
audithub_client/api/delete_organization.py
audithub_client/api/get_configuration.py
audithub_client/api/get_latest_version.py
audithub_client/api/get_my_organizations.py
audithub_client/api/get_my_profile.py
audithub_client/api/get_organization_users.py
audithub_client/api/get_organizations.py
audithub_client/api/get_project.py
audithub_client/api/get_task_archive.py
audithub_client/api/get_task_artifact.py
audithub_client/api/get_task_info.py
audithub_client/api/get_task_logs.py
audithub_client/api/get_users.py
audithub_client/api/get_version_archive.py
audithub_client/api/get_version_comments.py
audithub_client/api/models/__init__.py
audithub_client/api/monitor_task.py
audithub_client/api/put_organization_restrictions.py
audithub_client/api/qa_cleanup.py
audithub_client/api/remove_user_from_organization.py
audithub_client/api/send_digest.py
audithub_client/api/start_orca_task.py
audithub_client/api/start_picus_v2_task.py
audithub_client/api/start_vanguard_task.py
audithub_client/library/__init__.py
audithub_client/library/auth.py
audithub_client/library/context.py
audithub_client/library/http.py
audithub_client/library/http_download.py
audithub_client/library/invocation_common.py
audithub_client/library/json_dump.py
audithub_client/library/logging_level.py
audithub_client/library/net_utils.py
audithub_client/library/orca_utils.py
audithub_client/library/ssl.py
audithub_client/library/utils.py
audithub_client/py.typed
audithub_client/scripts/create_version_via_local_archive.py
audithub_client/scripts/create_version_via_url.py
audithub_client-1.1.12.dist-info/METADATA
audithub_client-1.1.12.dist-info/WHEEL
audithub_client-1.1.12.dist-info/entry_points.txt
audithub_client-1.1.12.dist-info/licenses/LICENSE
audithub_client-1.1.12.dist-info/RECORD
