Metadata-Version: 2.4
Name: audithub-client
Version: 1.1.12
Summary: A Python client that can access Veridise AuditHub via its REST API, providing CLI access
License: AGPLv3
License-File: LICENSE
Author: Nikos Chondros
Author-email: nikos@veridise.com
Requires-Python: >=3.12,<4.0
Classifier: License :: Other/Proprietary License
Classifier: Programming Language :: Python :: 3
Classifier: Programming Language :: Python :: 3.12
Classifier: Programming Language :: Python :: 3.13
Classifier: Programming Language :: Python :: 3.14
Requires-Dist: cyclopts
Requires-Dist: httpx
Requires-Dist: humanize
Requires-Dist: pydantic
Requires-Dist: tabulate
Requires-Dist: websockets
